<annotation>
	<folder>positive</folder>
	<filename>mug445.jpg</filename>
	<path>C:\Users\khode\Desktop\cascadeclassimug\positive\mug445.jpg</path>
	<source>
		<database>Unknown</database>
	</source>
	<size>
		<width>961</width>
		<height>1280</height>
		<depth>3</depth>
	</size>
	<segmented>0</segmented>
	<object>
		<name>mug</name>
		<pose>Unspecified</pose>
		<truncated>0</truncated>
		<difficult>0</difficult>
		<bndbox>
			<xmin>298</xmin>
			<ymin>474</ymin>
			<xmax>771</xmax>
			<ymax>926</ymax>
		</bndbox>
	</object>
</annotation>
